{"type":"auth/StdTx","value":{"msg":[{"type":"cosmos-sdk/MsgCreateValidator","value":{"description":{"moniker":"Chorus One","identity":"00B79D689B7DC1CE","website":"https://chorus.one","details":"Secure Regen and shape its future, and the future of the world, by delegating to Chorus One, a highly secure and stable validator. By delegating, you agree to the terms of service."},"commission":{"rate":"1.000000000000000000","max_rate":"1.000000000000000000","max_change_rate":"1.000000000000000000"},"min_self_delegation":"1","delegator_address":"xrn:140y8m6r7s40mvmz6g5dqrsrfvfkq5m8cu30tnv","validator_address":"xrn:valoper140y8m6r7s40mvmz6g5dqrsrfvfkq5m8c267452","pubkey":"xrn:valconspub1zcjduepqknswwqzjzquaqx9g69fhlfy98fygwr6aahdjj2zuvg052vaq3yssd7wfh3","value":{"denom":"tree","amount":"1000000000"}}}],"fee":{"amount":[],"gas":"200000"},"signatures":[{"pub_key":{"type":"tendermint/PubKeySecp256k1","value":"AkyRJw6I9NZ2JhLiifzxoSsHJl7KgY8jHm4L+MOoN87X"},"signature":"DiCuKdsBmQ0YzFCzwttISaT/7qsQGvjlQ5dNSXZvs45qMu2cCDX/piqFMxiNTLFgrRbrXRSRfy+GPfyy5e/d6g=="}],"memo":"4857aca8b6285ef4b5326c6002ed6d1d7d506a25@54.153.35.124:26656"}}

